kernprof.py
line_profiler/__init__.py
line_profiler/__main__.py
line_profiler/_line_profiler.cpython-39-darwin.so
line_profiler/line_profiler.py
line_profiler/line_profiler_py35.py
line_profiler_andy-3.1.0.dist-info/LICENSE.txt
line_profiler_andy-3.1.0.dist-info/LICENSE_Python.txt
line_profiler_andy-3.1.0.dist-info/METADATA
line_profiler_andy-3.1.0.dist-info/WHEEL
line_profiler_andy-3.1.0.dist-info/entry_points.txt
line_profiler_andy-3.1.0.dist-info/top_level.txt
line_profiler_andy-3.1.0.dist-info/RECORD
